argcomb.py
arg_comb-0.1.dist-info/LICENSE
arg_comb-0.1.dist-info/METADATA
arg_comb-0.1.dist-info/WHEEL
arg_comb-0.1.dist-info/top_level.txt
arg_comb-0.1.dist-info/RECORD
