Metadata-Version: 2.1
Name: arg-comb
Version: 0.1
Summary: Validate the argument combination passed to a function
Home-page: https://github.com/jacobunna/argcomb
Author: Jacob Unna
Author-email: jacob.unna@gmail.com
License: MIT
Keywords: argument parameter validation
Platform: UNKNOWN
Classifier: Development Status :: 3 - Alpha
Classifier: Intended Audience :: Developers
Classifier: License :: OSI Approved :: MIT License
Classifier: Programming Language :: Python :: 3.8
Classifier: Natural Language :: English 
Classifier: Typing :: Typed
Requires-Python: >=3.8
Provides-Extra: dev
Requires-Dist: pytest ; extra == 'dev'
Requires-Dist: sphinx ; extra == 'dev'
